cookiecutter_starter/__init__.py
cookiecutter_starter/__main__.py
cookiecutter_starter/main.py
cookiecutter_starter-0.2.0.dist-info/LICENSE
cookiecutter_starter-0.2.0.dist-info/METADATA
cookiecutter_starter-0.2.0.dist-info/WHEEL
cookiecutter_starter-0.2.0.dist-info/entry_points.txt
cookiecutter_starter-0.2.0.dist-info/RECORD
