Metadata-Version: 2.1
Name: cookiecutter-starter
Version: 0.2.0
Summary: 
Author: Abderrahim Guennoune
Author-email: aguennoune@outlook.com
Requires-Python: >=3.7,<4.0
Classifier: Programming Language :: Python :: 3
Classifier: Programming Language :: Python :: 3.7
Classifier: Programming Language :: Python :: 3.8
Classifier: Programming Language :: Python :: 3.9
Classifier: Programming Language :: Python :: 3.10
Classifier: Programming Language :: Python :: 3.11
Requires-Dist: click (>=8.1.7,<9.0.0)
Requires-Dist: typer[all] (>=0.9.0,<0.10.0)
